{
    "Default": {
        "history": {
            "localhost:5173": {
                "total_time_spent": "0:00:06",
                "visited_links": [
                    {
                        "url": "http://localhost:5173/",
                        "title": "Vite + React",
                        "timestamp": "2024-04-10 09:47:32",
                        "duration": "0:00:03",
                        "email": "rahilshaikh261001@gmail.com",
                        "full_name": "Rahil Shaikh"
                    },
                    {
                        "url": "http://localhost:5173/",
                        "title": "Vite + React",
                        "timestamp": "2024-04-10 09:47:29",
                        "duration": "0:00:03",
                        "email": "rahilshaikh261001@gmail.com",
                        "full_name": "Rahil Shaikh"
                    }
                ]
            }
        }
    },
    "Profile 1": {
        "history": {
            "localhost:5173": {
                "total_time_spent": "0:00:02",
                "visited_links": [
                    {
                        "url": "http://localhost:5173/",
                        "title": "Vite + React",
                        "timestamp": "2024-04-10 09:47:57",
                        "duration": "0:00:01",
                        "email": "sahilsk565678@gmail.com",
                        "full_name": "Sahil Shaikh"
                    },
                    {
                        "url": "http://localhost:5173/",
                        "title": "Vite + React",
                        "timestamp": "2024-04-10 09:47:56",
                        "duration": "0:00:01",
                        "email": "sahilsk565678@gmail.com",
                        "full_name": "Sahil Shaikh"
                    }
                ]
            }
        }
    },
    "Profile 3": {
        "history": {}
    },
    "Profile 4": {
        "history": {
            "mail.google.com": {
                "total_time_spent": "2:17:52",
                "visited_links": [
                    {
                        "url": "https://mail.google.com/mail/u/0/?tab=rm&ogbl#inbox",
                        "title": "Inbox (463) - vu2s2223012@pvppcoe.ac.in - Padmabhushan Vasantdada Patil Pratishthan\u2019s College of Engineering Mail",
                        "timestamp": "2024-04-10 10:52:57",
                        "duration": "0:00:00",
                        "email": "vu2s2223012@pvppcoe.ac.in",
                        "full_name": "SHAIKH SAHIL"
                    },
                    {
                        "url": "https://mail.google.com/mail/u/0/?tab=rm&ogbl#sent",
                        "title": "Sent Mail - vu2s2223012@pvppcoe.ac.in - Padmabhushan Vasantdada Patil Pratishthan\u2019s College of Engineering Mail",
                        "timestamp": "2024-04-10 10:52:38",
                        "duration": "0:08:02",
                        "email": "vu2s2223012@pvppcoe.ac.in",
                        "full_name": "SHAIKH SAHIL"
                    },
                    {
                        "url": "https://mail.google.com/mail/u/0/?tab=rm&ogbl#sent",
                        "title": "Sent Mail - vu2s2223012@pvppcoe.ac.in - Padmabhushan Vasantdada Patil Pratishthan\u2019s College of Engineering Mail",
                        "timestamp": "2024-04-10 10:52:38",
                        "duration": "0:08:02",
                        "email": "vu2s2223012@pvppcoe.ac.in",
                        "full_name": "SHAIKH SAHIL"
                    },
                    {
                        "url": "https://mail.google.com/mail/u/0/?tab=rm&ogbl#sent?compose=DmwnWsmDPkVbhpCvbxfccRNFlDFXgNmcwBfJMCtTxDhkMHMdmVXpZVGrBfCbmcGjjQbjRNRqdtRG",
                        "title": "Sent Mail - vu2s2223012@pvppcoe.ac.in - Padmabhushan Vasantdada Patil Pratishthan\u2019s College of Engineering Mail",
                        "timestamp": "2024-04-10 10:52:00",
                        "duration": "0:00:38",
                        "email": "vu2s2223012@pvppcoe.ac.in",
                        "full_name": "SHAIKH SAHIL"
                    },
                    {
                        "url": "https://mail.google.com/mail/u/0/?tab=rm&ogbl#sent?compose=DmwnWsmDPkVbhpCvbxfccRNFlDFXgNmcwBfJMCtTxDhkMHMdmVXpZVGrBfCbmcGjjQbjRNRqdtRG",
                        "title": "Sent Mail - vu2s2223012@pvppcoe.ac.in - Padmabhushan Vasantdada Patil Pratishthan\u2019s College of Engineering Mail",
                        "timestamp": "2024-04-10 10:52:00",
                        "duration": "0:00:38",
                        "email": "vu2s2223012@pvppcoe.ac.in",
                        "full_name": "SHAIKH SAHIL"
                    },
                    {
                        "url": "https://mail.google.com/mail/u/0/?tab=rm&ogbl#sent?compose=new",
                        "title": "Sent Mail - vu2s2223012@pvppcoe.ac.in - Padmabhushan Vasantdada Patil Pratishthan\u2019s College of Engineering Mail",
                        "timestamp": "2024-04-10 10:51:56",
                        "duration": "0:00:04",
                        "email": "vu2s2223012@pvppcoe.ac.in",
                        "full_name": "SHAIKH SAHIL"
                    },
                    {
                        "url": "https://mail.google.com/mail/u/0/?tab=rm&ogbl#sent?compose=new",
                        "title": "Sent Mail - vu2s2223012@pvppcoe.ac.in - Padmabhushan Vasantdada Patil Pratishthan\u2019s College of Engineering Mail",
                        "timestamp": "2024-04-10 10:51:56",
                        "duration": "0:00:04",
                        "email": "vu2s2223012@pvppcoe.ac.in",
                        "full_name": "SHAIKH SAHIL"
                    },
                    {
                        "url": "https://mail.google.com/mail/u/0/?tab=rm&ogbl#sent",
                        "title": "Sent Mail - vu2s2223012@pvppcoe.ac.in - Padmabhushan Vasantdada Patil Pratishthan\u2019s College of Engineering Mail",
                        "timestamp": "2024-04-10 10:44:39",
                        "duration": "0:08:02",
                        "email": "vu2s2223012@pvppcoe.ac.in",
                        "full_name": "SHAIKH SAHIL"
                    },
                    {
                        "url": "https://mail.google.com/mail/u/0/?tab=rm&ogbl#sent",
                        "title": "Sent Mail - vu2s2223012@pvppcoe.ac.in - Padmabhushan Vasantdada Patil Pratishthan\u2019s College of Engineering Mail",
                        "timestamp": "2024-04-10 10:44:39",
                        "duration": "0:08:02",
                        "email": "vu2s2223012@pvppcoe.ac.in",
                        "full_name": "SHAIKH SAHIL"
                    },
                    {
                        "url": "https://mail.google.com/mail/u/0/?tab=rm&ogbl#sent/QgrcJHrnxVBgfsHTPjvmxchbSfSQBjGgFzQ",
                        "title": "ML Update Practical 6 to 9 - vu2s2223012@pvppcoe.ac.in - Padmabhushan Vasantdada Patil Pratishthan\u2019s College of Engineering Mail",
                        "timestamp": "2024-04-10 10:44:03",
                        "duration": "0:00:36",
                        "email": "vu2s2223012@pvppcoe.ac.in",
                        "full_name": "SHAIKH SAHIL"
                    },
                    {
                        "url": "https://mail.google.com/mail/u/0/?tab=rm&ogbl#sent/QgrcJHrnxVBgfsHTPjvmxchbSfSQBjGgFzQ",
                        "title": "ML Update Practical 6 to 9 - vu2s2223012@pvppcoe.ac.in - Padmabhushan Vasantdada Patil Pratishthan\u2019s College of Engineering Mail",
                        "timestamp": "2024-04-10 10:44:03",
                        "duration": "0:00:36",
                        "email": "vu2s2223012@pvppcoe.ac.in",
                        "full_name": "SHAIKH SAHIL"
                    },
                    {
                        "url": "https://mail.google.com/mail/u/0/?tab=rm&ogbl#sent",
                        "title": "Sent Mail - vu2s2223012@pvppcoe.ac.in - Padmabhushan Vasantdada Patil Pratishthan\u2019s College of Engineering Mail",
                        "timestamp": "2024-04-10 10:43:46",
                        "duration": "0:08:02",
                        "email": "vu2s2223012@pvppcoe.ac.in",
                        "full_name": "SHAIKH SAHIL"
                    },
                    {
                        "url": "https://mail.google.com/mail/u/0/?tab=rm&ogbl#sent",
                        "title": "Sent Mail - vu2s2223012@pvppcoe.ac.in - Padmabhushan Vasantdada Patil Pratishthan\u2019s College of Engineering Mail",
                        "timestamp": "2024-04-10 10:43:46",
                        "duration": "0:08:02",
                        "email": "vu2s2223012@pvppcoe.ac.in",
                        "full_name": "SHAIKH SAHIL"
                    },
                    {
                        "url": "https://mail.google.com/mail/u/0/?tab=rm&ogbl#sent/QgrcJHsNnjdLnsdDsCJPlbgnWVBSXrRkGwg",
                        "title": "DAV Practical 1 to 7 - vu2s2223012@pvppcoe.ac.in - Padmabhushan Vasantdada Patil Pratishthan\u2019s College of Engineering Mail",
                        "timestamp": "2024-04-10 10:42:57",
                        "duration": "0:09:27",
                        "email": "vu2s2223012@pvppcoe.ac.in",
                        "full_name": "SHAIKH SAHIL"
                    },
                    {
                        "url": "https://mail.google.com/mail/u/0/?tab=rm&ogbl#sent/QgrcJHsNnjdLnsdDsCJPlbgnWVBSXrRkGwg",
                        "title": "DAV Practical 1 to 7 - vu2s2223012@pvppcoe.ac.in - Padmabhushan Vasantdada Patil Pratishthan\u2019s College of Engineering Mail",
                        "timestamp": "2024-04-10 10:42:57",
                        "duration": "0:09:27",
                        "email": "vu2s2223012@pvppcoe.ac.in",
                        "full_name": "SHAIKH SAHIL"
                    },
                    {
                        "url": "https://mail.google.com/mail/u/0/?tab=rm&ogbl#sent",
                        "title": "Sent Mail - vu2s2223012@pvppcoe.ac.in - Padmabhushan Vasantdada Patil Pratishthan\u2019s College of Engineering Mail",
                        "timestamp": "2024-04-10 10:42:54",
                        "duration": "0:08:02",
                        "email": "vu2s2223012@pvppcoe.ac.in",
                        "full_name": "SHAIKH SAHIL"
                    },
                    {
                        "url": "https://mail.google.com/mail/u/0/?tab=rm&ogbl#sent",
                        "title": "Sent Mail - vu2s2223012@pvppcoe.ac.in - Padmabhushan Vasantdada Patil Pratishthan\u2019s College of Engineering Mail",
                        "timestamp": "2024-04-10 10:42:54",
                        "duration": "0:08:02",
                        "email": "vu2s2223012@pvppcoe.ac.in",
                        "full_name": "SHAIKH SAHIL"
                    },
                    {
                        "url": "https://mail.google.com/mail/u/0/?tab=rm&ogbl#sent/QgrcJHsbdJHXjbzzBBxZXXGptTGjCVpjctQ",
                        "title": "SEPM Practical 1 to 10 - vu2s2223012@pvppcoe.ac.in - Padmabhushan Vasantdada Patil Pratishthan\u2019s College of Engineering Mail",
                        "timestamp": "2024-04-10 10:42:27",
                        "duration": "0:00:27",
                        "email": "vu2s2223012@pvppcoe.ac.in",
                        "full_name": "SHAIKH SAHIL"
                    },
                    {
                        "url": "https://mail.google.com/mail/u/0/?tab=rm&ogbl#sent/QgrcJHsbdJHXjbzzBBxZXXGptTGjCVpjctQ",
                        "title": "SEPM Practical 1 to 10 - vu2s2223012@pvppcoe.ac.in - Padmabhushan Vasantdada Patil Pratishthan\u2019s College of Engineering Mail",
                        "timestamp": "2024-04-10 10:42:27",
                        "duration": "0:00:27",
                        "email": "vu2s2223012@pvppcoe.ac.in",
                        "full_name": "SHAIKH SAHIL"
                    },
                    {
                        "url": "https://mail.google.com/mail/u/0/?tab=rm&ogbl#sent",
                        "title": "Sent Mail - vu2s2223012@pvppcoe.ac.in - Padmabhushan Vasantdada Patil Pratishthan\u2019s College of Engineering Mail",
                        "timestamp": "2024-04-10 10:42:24",
                        "duration": "0:08:02",
                        "email": "vu2s2223012@pvppcoe.ac.in",
                        "full_name": "SHAIKH SAHIL"
                    },
                    {
                        "url": "https://mail.google.com/mail/u/0/?tab=rm&ogbl#sent",
                        "title": "Sent Mail - vu2s2223012@pvppcoe.ac.in - Padmabhushan Vasantdada Patil Pratishthan\u2019s College of Engineering Mail",
                        "timestamp": "2024-04-10 10:42:24",
                        "duration": "0:08:02",
                        "email": "vu2s2223012@pvppcoe.ac.in",
                        "full_name": "SHAIKH SAHIL"
                    },
                    {
                        "url": "https://mail.google.com/mail/u/0/?tab=rm&ogbl#sent/QgrcJHsNnjdLnsdDsCJPlbgnWVBSXrRkGwg",
                        "title": "DAV Practical 1 to 7 - vu2s2223012@pvppcoe.ac.in - Padmabhushan Vasantdada Patil Pratishthan\u2019s College of Engineering Mail",
                        "timestamp": "2024-04-10 10:33:46",
                        "duration": "0:09:27",
                        "email": "vu2s2223012@pvppcoe.ac.in",
                        "full_name": "SHAIKH SAHIL"
                    },
                    {
                        "url": "https://mail.google.com/mail/u/0/?tab=rm&ogbl#sent/QgrcJHsNnjdLnsdDsCJPlbgnWVBSXrRkGwg",
                        "title": "DAV Practical 1 to 7 - vu2s2223012@pvppcoe.ac.in - Padmabhushan Vasantdada Patil Pratishthan\u2019s College of Engineering Mail",
                        "timestamp": "2024-04-10 10:33:46",
                        "duration": "0:09:27",
                        "email": "vu2s2223012@pvppcoe.ac.in",
                        "full_name": "SHAIKH SAHIL"
                    },
                    {
                        "url": "https://mail.google.com/mail/u/0/?tab=rm&ogbl#sent",
                        "title": "Sent Mail - vu2s2223012@pvppcoe.ac.in - Padmabhushan Vasantdada Patil Pratishthan\u2019s College of Engineering Mail",
                        "timestamp": "2024-04-10 10:33:43",
                        "duration": "0:08:02",
                        "email": "vu2s2223012@pvppcoe.ac.in",
                        "full_name": "SHAIKH SAHIL"
                    },
                    {
                        "url": "https://mail.google.com/mail/u/0/?tab=rm&ogbl#sent",
                        "title": "Sent Mail - vu2s2223012@pvppcoe.ac.in - Padmabhushan Vasantdada Patil Pratishthan\u2019s College of Engineering Mail",
                        "timestamp": "2024-04-10 10:33:43",
                        "duration": "0:08:02",
                        "email": "vu2s2223012@pvppcoe.ac.in",
                        "full_name": "SHAIKH SAHIL"
                    },
                    {
                        "url": "https://mail.google.com/mail/u/0/?tab=rm&ogbl#inbox/QgrcJHsNnjdLnsdDsCJPlbgnWVBSXrRkGwg",
                        "title": "DAV Practical 1 to 7 - vu2s2223012@pvppcoe.ac.in - Padmabhushan Vasantdada Patil Pratishthan\u2019s College of Engineering Mail",
                        "timestamp": "2024-04-10 10:33:33",
                        "duration": "0:00:10",
                        "email": "vu2s2223012@pvppcoe.ac.in",
                        "full_name": "SHAIKH SAHIL"
                    }
                ]
            }
        }
    },
    "Profile 5": {
        "history": {}
    },
    "Profile 6": {
        "history": {}
    }
}